mapboxcli/__init__.py
mapboxcli/__main__.py
mapboxcli/compat.py
mapboxcli/errors.py
mapboxcli/scripts/__init__.py
mapboxcli/scripts/cli.py
mapboxcli/scripts/config.py
mapboxcli/scripts/datasets.py
mapboxcli/scripts/directions.py
mapboxcli/scripts/geocoding.py
mapboxcli/scripts/mapmatching.py
mapboxcli/scripts/static.py
mapboxcli/scripts/uploads.py
mapboxcli-0.8.0.dist-info/METADATA
mapboxcli-0.8.0.dist-info/RECORD
mapboxcli-0.8.0.dist-info/WHEEL
mapboxcli-0.8.0.dist-info/entry_points.txt
mapboxcli-0.8.0.dist-info/top_level.txt
